{
  "appCodeName": "Mozilla",
  "appName": "Netscape",
  "appVersion": "5.0 (Windows NT 10.0; Win64; x64) AppleWebKit/537.36 (KHTML, like Gecko) Chrome/122.0.0.0 Safari/537.36",
  "connection": "other",
  "doNotTrack": "",
  "hardwareConcurrency": 8,
  "language": "zh",
  "languages": "zh",
  "maxTouchPoints": 0,
  "mimeTypes": "application/pdf,text/pdf",
  "platform": "Win32",
  "plugins": "PDF Viewer,Chrome PDF Viewer,Chromium PDF Viewer,Microsoft Edge PDF Viewer,WebKit built-in PDF",
  "userAgent": "Mozilla/5.0 (Windows NT 10.0; Win64; x64) AppleWebKit/537.36 (KHTML, like Gecko) Chrome/122.0.0.0 Safari/537.36",
  "colorDepth": 24,
  "pixelDepth": 24,
  "screenResolution": "1920x1080",
  "timezoneOffset": -480,
  "sessionStorage": true,
  "localStorage": true,
  "indexedDB": true,
  "cookie": true,
  "adBlock": false,
  "devicePixelRatio": 1,
  "hasLiedOs": false,
  "hasLiedLanguages": false,
  "hasLiedResolution": false,
  "hasLiedBrowser": false,
  "webglRenderer": "ANGLE (Intel, Intel(R) HD Graphics 530 (0x0000191B) Direct3D11 vs_5_0 ps_5_0, D3D11)",
  "webglVendor": "Google Inc. (Intel)",
  "canvas": "db58e2b28a6f57120c5364eabd3bd2a2",
  "fonts": "Arial,Arial Black,Arial Narrow,Calibri,Cambria,Cambria Math,Comic Sans MS,Consolas,Courier,Courier New,Georgia,Helvetica,Impact,Lucida Console,Lucida Sans Unicode,Microsoft Sans Serif,MS Gothic,MS PGothic,MS Sans Serif,MS Serif,Palatino Linotype,Segoe Print,Segoe Script,Segoe UI,Segoe UI Light,Segoe UI Semibold,Segoe UI Symbol,Tahoma,Times,Times New Roman,Trebuchet MS,Verdana,Wingdings,Candara,Constantia,Corbel,Ebrima,FangSong,Gabriola,KaiTi,Malgun Gothic,Marlett,Microsoft Himalaya,Microsoft JhengHei,Microsoft New Tai Lue,Microsoft PhagsPa,Microsoft Tai Le,Microsoft YaHei,Microsoft Yi Baiti,MingLiU_HKSCS-ExtB,MingLiU-ExtB,Mongolian Baiti,MS UI Gothic,MT Extra,MV Boli,NSimSun,PMingLiU-ExtB,SimHei,SimSun,SimSun-ExtB,Sylfaen",
  "dt": "2024-02-24",
  "time": "2024-02-24 03:36:52",
  "userid": "",
  "mid": "b4d1ed918bb86ebbae629fe7ece1a783",
  "uuid": "73b74ff3d330481db755df420ec3b08d",
  "appid": "1014",
  "webdriver": false,
  "callPhantom": false,
  "tempKgMid": "",
  "referrer": "",
  "source": "https://www.kugou.com/yy/html/search.html#searchType=song&searchKeyWord=",
  "clientAppid": "",
  "clientver": "",
  "clientMid": "",
  "clientDfid": "",
  "clientUserId": "",
  "audioKey": "124.04347527516074"
}